minelert_utils/__init__.py
minelert_utils/reader.py
minelert_utils/tag.py
minelert_utils-1.0.0.dist-info/LICENSE
minelert_utils-1.0.0.dist-info/METADATA
minelert_utils-1.0.0.dist-info/WHEEL
minelert_utils-1.0.0.dist-info/top_level.txt
minelert_utils-1.0.0.dist-info/RECORD
