Metadata-Version: 2.1
Name: minelert-utils
Version: 1.0.0
Summary: Minelert utility package
Home-page: https://github.com/dpventer/minelert_utils
Author: Niel Venter
Author-email: support@minelert.com
License: MIT
Platform: UNKNOWN
Classifier: Programming Language :: Python :: 3
Classifier: License :: OSI Approved :: MIT License
Classifier: Operating System :: OS Independent
Requires-Dist: pySerial
